ivy/__init__.py
ivy/_version.py
ivy/func_wrapper.py
ivy/compiler/_compiler.so
ivy/compiler/_compiler_38.so
ivy/compiler/compiler.py
ivy/compiler/utils/III.cpython-310-x86_64-linux-gnu.so
ivy/compiler/utils/III.so
ivy/compiler/utils/IIII.cpython-310-x86_64-linux-gnu.so
ivy/compiler/utils/IIII_38.cpython-38-x86_64-linux-gnu.so
ivy/compiler/utils/III_38.cpython-38-x86_64-linux-gnu.so
ivy/compiler/utils/IIV.cpython-310-x86_64-linux-gnu.so
ivy/compiler/utils/IIV.so
ivy/compiler/utils/IIV_38.cpython-38-x86_64-linux-gnu.so
ivy/compiler/utils/IIX.cpython-310-x86_64-linux-gnu.so
ivy/compiler/utils/IIX.so
ivy/compiler/utils/IIX_38.cpython-38-x86_64-linux-gnu.so
ivy/compiler/utils/IVI.cpython-310-x86_64-linux-gnu.so
ivy/compiler/utils/IVI.so
ivy/compiler/utils/IVI_38.cpython-38-x86_64-linux-gnu.so
ivy/compiler/utils/IVV.cpython-310-x86_64-linux-gnu.so
ivy/compiler/utils/IVV.so
ivy/compiler/utils/IVV_38.cpython-38-x86_64-linux-gnu.so
ivy/compiler/utils/IXI.cpython-310-x86_64-linux-gnu.so
ivy/compiler/utils/IXI.so
ivy/compiler/utils/IXI_38.cpython-38-x86_64-linux-gnu.so
ivy/compiler/utils/IXV.cpython-310-x86_64-linux-gnu.so
ivy/compiler/utils/IXV.so
ivy/compiler/utils/IXV_38.cpython-38-x86_64-linux-gnu.so
ivy/compiler/utils/IXX.cpython-310-x86_64-linux-gnu.so
ivy/compiler/utils/IXX.so
ivy/compiler/utils/IXX_38.cpython-38-x86_64-linux-gnu.so
ivy/compiler/utils/VII.cpython-310-x86_64-linux-gnu.so
ivy/compiler/utils/VII.so
ivy/compiler/utils/VII_38.cpython-38-x86_64-linux-gnu.so
ivy/compiler/utils/VIV.cpython-310-x86_64-linux-gnu.so
ivy/compiler/utils/VIV.so
ivy/compiler/utils/VIV_38.cpython-38-x86_64-linux-gnu.so
ivy/compiler/utils/VIX.cpython-310-x86_64-linux-gnu.so
ivy/compiler/utils/VIX.so
ivy/compiler/utils/VIX_38.cpython-38-x86_64-linux-gnu.so
ivy/compiler/utils/VVI.cpython-310-x86_64-linux-gnu.so
ivy/compiler/utils/VVI.so
ivy/compiler/utils/VVI_38.cpython-38-x86_64-linux-gnu.so
ivy/compiler/utils/VVV.cpython-310-x86_64-linux-gnu.so
ivy/compiler/utils/VVV.so
ivy_testing_release-0.0.0.1.dist-info/LICENSE
ivy_testing_release-0.0.0.1.dist-info/METADATA
ivy_testing_release-0.0.0.1.dist-info/WHEEL
ivy_testing_release-0.0.0.1.dist-info/top_level.txt
ivy_testing_release-0.0.0.1.dist-info/RECORD
