Metadata-Version: 2.1
Name: ivy-testing-release
Version: 0.0.0.1
Summary: The unified machine learning framework, enabling framework-agnostic functions, layers and libraries.
Home-page: https://unify.ai/ivy
Author: Unify
Author-email: hello@unify.ai
License: Apache 2.0
Project-URL: Docs, https://unify.ai/docs/ivy/
Project-URL: Source, https://github.com/unifyai/ivy
Classifier: License :: OSI Approved :: Apache Software License
License-File: LICENSE
Requires-Dist: numpy
Requires-Dist: einops
Requires-Dist: psutil
Requires-Dist: termcolor
Requires-Dist: colorama
Requires-Dist: packaging
Requires-Dist: nvidia-ml-py
Requires-Dist: diskcache
Requires-Dist: google-auth
Requires-Dist: requests
Requires-Dist: pyvis
Requires-Dist: dill
